themap/BERT.py
themap/__init__.py
themap/model.py
themap/net.py
themap/utils.py
themap_tools-1.0.0.dist-info/LICENSE
themap_tools-1.0.0.dist-info/METADATA
themap_tools-1.0.0.dist-info/WHEEL
themap_tools-1.0.0.dist-info/top_level.txt
themap_tools-1.0.0.dist-info/RECORD
